{"air_date":"2016-03-04T00:00:00.0000000Z","episode_number":9,"name":"第 48 章","overview":"在大会上，弗兰克和他的团队表面上要推动凯瑟琳·杜兰特成为他的竞选伙伴，然而私下里却另有打算。","id":1148725,"production_code":"HOC-409","season_number":4,"still_path":"/al9EvPl9huoVdAnTlYj9RlNAr4E.jpg","vote_average":8.5,"vote_count":29,"images":{"stills":[{"aspect_ratio":1.778,"file_path":"/al9EvPl9huoVdAnTlYj9RlNAr4E.jpg","height":1080,"vote_average":0,"vote_count":0,"width":1920}]},"external_ids":{"imdb_id":"tt5083704","tvdb_id":5440812,"tvrage_id":1065900286},"credits":{"cast":[{"adult":false,"gender":2,"id":1979,"known_for_department":"Acting","name":"凯文·史派西","original_name":"Kevin Spacey","popularity":2.6939,"profile_path":"/nPrUZDEbGQe6jwpVbHKJCXsMd7r.jpg","cast_id":0,"character":"Frank Underwood","credit_id":"526e411419c2954312021cb2","order":0},{"adult":false,"gender":1,"id":32,"known_for_department":"Acting","name":"罗宾·怀特","original_name":"Robin Wright","popularity":4.213,"profile_path":"/d3rIv0y2p0jMsQ7ViR7O1606NZa.jpg","cast_id":0,"character":"Claire Underwood","credit_id":"5256da6519c2956ff60b467f","order":1},{"adult":false,"gender":2,"id":50217,"known_for_department":"Acting","name":"迈克尔·凯利","original_name":"Michael Kelly","popularity":1.8042,"profile_path":"/6MI8HhX1GWbcrWG8DiHffzmqaVm.jpg","cast_id":0,"character":"Doug Stamper","credit_id":"5256da6519c2956ff60b46c5","order":2},{"adult":false,"gender":1,"id":9206,"known_for_department":"Acting","name":"内芙·坎贝尔","original_name":"Neve Campbell","popularity":3.1695,"profile_path":"/8DZiZ0TyKguNFYSn603rtIUzNOw.jpg","cast_id":0,"character":"LeAnn Harvey","credit_id":"5a82e6f8925141167e011024","order":9},{"adult":false,"gender":1,"id":18261,"known_for_department":"Acting","name":"杰恩·阿特金森","original_name":"Jayne Atkinson","popularity":0.9152,"profile_path":"/9IOlElVs5FxWLdW6mnfToHaOxY7.jpg","cast_id":0,"character":"Catherine Durant","credit_id":"58d8f1d9925141445f021b9d","order":10},{"adult":false,"gender":2,"id":60117,"known_for_department":"Acting","name":"德里克·塞西尔","original_name":"Derek Cecil","popularity":0.7787,"profile_path":"/javfOSjgOmviExZdZgQJCyToqVW.jpg","cast_id":0,"character":"Seth Grayson","credit_id":"5a117eb6c3a368627d0550a2","order":15},{"adult":false,"gender":2,"id":92404,"known_for_department":"Acting","name":"乔尔·金纳曼","original_name":"Joel Kinnaman","popularity":2.6426,"profile_path":"/iVTh89rxgPhZSuijVo467WNsvUw.jpg","cast_id":0,"character":"Will Conway","credit_id":"5a0c082dc3a36875d600b852","order":25},{"adult":false,"gender":2,"id":167564,"known_for_department":"Acting","name":"保罗·斯帕克斯","original_name":"Paul Sparks","popularity":0.8089,"profile_path":"/oQemFTD6VraSIeOJ1Jcr58iGHNF.jpg","cast_id":0,"character":"Thomas Yates","credit_id":"5cc261f09251417d39000a92","order":33}],"crew":[{"adult":false,"gender":2,"id":172179,"known_for_department":"Writing","name":"Frank Pugliese","original_name":"Frank Pugliese","popularity":0.1118,"credit_id":"5830438392514162c000e380","department":"Writing","job":"Writer"},{"adult":false,"gender":1,"id":32,"known_for_department":"Acting","name":"罗宾·怀特","original_name":"Robin Wright","popularity":4.213,"profile_path":"/d3rIv0y2p0jMsQ7ViR7O1606NZa.jpg","credit_id":"56da35da925141465c000684","department":"Directing","job":"Director"},{"adult":false,"gender":2,"id":3090971,"known_for_department":"Production","name":"Hameed Shaukat","original_name":"Hameed Shaukat","popularity":0.1166,"profile_path":"/dAWWs4MDEI3XgAE20CrANnQxhNb.jpg","credit_id":"64a4596a8c44b9012d6b6f4b","department":"Production","job":"Producer"}],"guest_stars":[{"id":115146,"name":"多米妮克·麦克艾丽戈特","credit_id":"5a117cb3c3a368628904c0c9","character":"Hannah Conway","order":14,"profile_path":"/pA6jcdqj05YQEVukE81a1hWx4NA.jpg"},{"id":1348457,"name":"安德鲁·波尔克","credit_id":"5cc273360e0a266b9600153c","character":"Harry Marshall","order":563,"profile_path":"/vCg49XCp79OOQAFiICuU7I79yXy.jpg"},{"id":10132,"name":"科鲁姆·费奥瑞","credit_id":"5cc271d40e0a26105af9e4e5","character":"Ted Brockhart","order":565,"profile_path":"/jeotIVor4fH3oqxkRZ6qyUbgrJ3.jpg"},{"id":64908,"name":"丽莎·盖伊·汉密尔顿","credit_id":"5cc2a1a9c3a3681e6b80b6c7","character":"Celia Jones","order":600,"profile_path":"/bqfowff4gF0cGaQ1c7F89HAL3DH.jpg"},{"id":163774,"name":"里德·伯尼","credit_id":"5cc268f19251412ba1f67b98","character":"Donald Blythe","order":609,"profile_path":"/dfLgNLUt6Xs2MJJTi6B1iWdXjU6.jpg"},{"id":163775,"name":"John C. Vennema","credit_id":"64a4597d8c44b9012d6b6f5a","character":"Senator Sheer","order":642,"profile_path":"/gx1PrG9r10366c2J5kpSkPIU2DX.jpg"},{"id":85566,"name":"Doug Barron","credit_id":"64a4598b158c8500acb380b3","character":"Senator Baker","order":643},{"id":1918377,"name":"Finn Douglas","credit_id":"64a459975a991500adf7b818","character":"Charlie Conway","order":644,"profile_path":"/4561787FlTTd28TzH905glN90rt.jpg"},{"id":1378739,"name":"Donnie Kehr","credit_id":"64a459a5158c85013945e519","character":"Adam Gould","order":645,"profile_path":"/wRhKjMZ0O5un3fX3oOIF4TFH4KG.jpg"},{"id":4146975,"name":"Susanne Arrington","credit_id":"64a459be1bf26600acae256d","character":"Tennessee Chair","order":646},{"id":1681737,"name":"Gilbert Cruz","credit_id":"64a459ccda10f000c592e830","character":"Texas Chair","order":647,"profile_path":"/i8PBTzRh8fKAWRMXOnQQkKJ3ctk.jpg"},{"id":1807327,"name":"Randall Taylor","credit_id":"64a459db8c44b900ae5fd4b9","character":"Alabama Chair","order":648,"profile_path":"/p8ROAbBpSkgoamYsOK2wxeh33em.jpg"},{"id":4146978,"name":"Maura Claire Harford","credit_id":"64a459f11bf26600c78982fb","character":"Alaska Chair","order":649},{"id":4146980,"name":"Demetria Joyce Bailey","credit_id":"64a45a0f8c44b900ae5fd4d9","character":"California Chair","order":650},{"id":4146983,"name":"Alan Wade","credit_id":"64a45a38158c8500c5c544ce","character":"Delaware Chair","order":651},{"id":196181,"name":"Ann Harada","credit_id":"64a45a45158c8500c5c544d8","character":"Hawaii Chair","order":652,"profile_path":"/AlBue8hWw5MnygmGvEbE4v14GOQ.jpg"},{"id":1853390,"name":"Alan Richmond","credit_id":"64a45a53158c8500ffb9cbf2","character":"Indiana Chair","order":653},{"id":4146985,"name":"Scott Lehman","credit_id":"64a45a7d1bf26600e693ef2e","character":"Louisiana Chair","order":654},{"id":1508943,"name":"Jake Tapper","credit_id":"64a45a8ca0be2800ecfcbbf0","character":"Jake Tapper","order":655,"profile_path":"/oUmhEkHiDe1k1bbyD0kPdXISeZk.jpg"},{"id":175194,"name":"Paul Begala","credit_id":"64a45a951bf26601431b3f09","character":"Paul Begala","order":656,"profile_path":"/wVBvYJvcJcjARpArthnoCeWPCqv.jpg"},{"id":1834657,"name":"莎拉·伊丽莎白·库普","credit_id":"64a45a9fda10f001397bb7e1","character":"Self","order":657,"profile_path":"/5sYIn144iOXNHyNkqDMvJerhmIW.jpg"},{"id":1025680,"name":"范·琼斯","credit_id":"64a45aa91bf26600acae2614","character":"Van Jones","order":658,"profile_path":"/lh6KOxZiM90jk2swWpsRB0UxTW0.jpg"},{"id":1704672,"name":"David Shae","credit_id":"64a45af21bf26601241f3ad4","character":"Buha","order":659,"profile_path":"/tBfDhXA1KlmdgVtuAgKX6C8QJWz.jpg"},{"id":3976940,"name":"Susan Rome","credit_id":"64a45b01158c8500ffb9cc60","character":"Danny's Mother","order":660},{"id":1432220,"name":"Shaira Barton","credit_id":"64a45b0ea0be2800aed4e547","character":"Luisa's Mother","order":661},{"id":557097,"name":"Tasia Grant","credit_id":"64a45b1a1bf26600e693efa7","character":"Reporter 1","order":662,"profile_path":"/hZYcduA3OuM49LMegV9P1wfVyCV.jpg"},{"id":1408786,"name":"Lauren O'Quinn","credit_id":"64a45b28da10f001397bb84f","character":"Reporter 2","order":663,"profile_path":"/to7mUgK6KGIGPch8zftjiujG8NW.jpg"},{"id":4146990,"name":"Cynthia Steele Vance","credit_id":"64a45b3ca0be2800ecfcbc58","character":"Reporter 3","order":664},{"id":4146991,"name":"Sanjay Raja","credit_id":"64a45b49158c85011c83ff36","character":"Reporter 4","order":665},{"id":24592,"name":"Kelly Miller","credit_id":"64a45b8b5a991501007cdee5","character":"News Correspondent","order":666,"profile_path":"/8vkFd1R1OWsEw0ih0qEfIxF6AvO.jpg"},{"id":1038939,"name":"Mike Lutz","credit_id":"64a45bbda0be2800cbf5c182","character":"Speechwriter 1","order":667,"profile_path":"/bgFYBFips9NX3gyZqAUksv3b4jM.jpg"},{"id":1905773,"name":"Felicia Greenfield","credit_id":"64a45bcc8c44b9012d6b70e8","character":"Speechwriter 2","order":668},{"id":3337095,"name":"Frank Sesno","credit_id":"64a45bdaa0be2800ecfcbca4","character":"News Anchor","order":669},{"id":4146996,"name":"Taylor Thomas","credit_id":"64a45c1e158c85013945e6da","character":"News Anchor","order":670},{"id":3260357,"name":"Lee Ordeman","credit_id":"64a45c2ca0be28010df19ab1","character":"News Anchor","order":671},{"id":4146997,"name":"Carolyn Presutti","credit_id":"64a45c398c44b9012d6b7138","character":"News Anchor","order":672},{"id":4147000,"name":"Melanie Hastings","credit_id":"64a45c46da10f000c592e9e8","character":"News Anchor","order":673},{"id":2520427,"name":"Jessica Kartalija","credit_id":"64a45c548c44b900ebe86588","character":"News Anchor","order":674},{"id":2232661,"name":"Jonathan D. Williams","credit_id":"64a45c648c44b9010c9c662f","character":"News Anchor","order":675,"profile_path":"/7l9EjuOdDFxyY0LOM90nxJgZBU3.jpg"},{"id":1476046,"name":"Bobby Kruger","credit_id":"64a45c728c44b900ebe86599","character":"Durant's Staffer","order":676},{"id":3256051,"name":"Craig Galloway","credit_id":"64a45c845a991501007cdf6e","character":"Secret Service Agent","order":677},{"id":4147004,"name":"Katrina Clark","credit_id":"64a45c9cda10f001397bb92a","character":"Sign Language Interpreter","order":678}]},"videos":{"results":[]}}